BrowserInfo3/Browsers.py
BrowserInfo3/Utilities.py
BrowserInfo3/__init__.py
BrowserInfo3/chrome.py
BrowserInfo3/edge.py
BrowserInfo3-0.1.dist-info/METADATA
BrowserInfo3-0.1.dist-info/WHEEL
BrowserInfo3-0.1.dist-info/top_level.txt
BrowserInfo3-0.1.dist-info/RECORD
