Metadata-Version: 2.1
Name: BrowserInfo3
Version: 0.1
Summary: An edge and chrome password, history logger, dont use it illegally. 
Author: pyprojects3
License: MIT
Keywords: Browser,BrowserHistory,SQL,Chrome,Edge,Passwords
Classifier: Development Status :: 1 - Planning
Classifier: Intended Audience :: Developers
Classifier: Programming Language :: Python :: 3
Classifier: Operating System :: Microsoft :: Windows
Requires-Dist: pywin32
Requires-Dist: pycryptodome
Requires-Dist: requests
